simmate/__init__.py
simmate/conftest.py
simmate/apps/__init__.py
simmate/apps/configs.py
simmate/apps/aflow/__init__.py
simmate/apps/aflow/migrations/0001_initial.py
simmate/apps/aflow/migrations/__init__.py
simmate/apps/aflow/models/__init__.py
simmate/apps/aflow/models/prototypes.py
simmate/apps/aflow/models/structures.py
simmate/apps/badelf/__init__.py
simmate/apps/badelf/configuration.py
simmate/apps/badelf/core/__init__.py
simmate/apps/badelf/core/badelf.py
simmate/apps/badelf/core/elf_analyzer.py
simmate/apps/badelf/core/partitioning.py
simmate/apps/badelf/core/voxel_assignment.py
simmate/apps/badelf/migrations/0001_initial.py
simmate/apps/badelf/migrations/0002_badelf_electrides_per_formula.py
simmate/apps/badelf/migrations/0003_badelf_electrides_per_reduced_formula.py
simmate/apps/badelf/migrations/0004_badelf_elf_maxima_elfionicradii.py
simmate/apps/badelf/migrations/0005_rename_dim_cutoffs_badelf_electride_dim_cutoffs_and_more.py
simmate/apps/badelf/migrations/0006_rename_charges_badelf_atom_charges_and_more.py
simmate/apps/badelf/migrations/__init__.py
simmate/apps/badelf/models/__init__.py
simmate/apps/badelf/models/badelf.py
simmate/apps/badelf/workflows/__init__.py
simmate/apps/badelf/workflows/badelf.py
simmate/apps/badelf/workflows/base.py
simmate/apps/bader/__init__.py
simmate/apps/bader/configuration.py
simmate/apps/bader/inputs.py
simmate/apps/bader/outputs/__init__.py
simmate/apps/bader/outputs/acf.py
simmate/apps/bader/toolkit/__init__.py
simmate/apps/bader/toolkit/grid.py
simmate/apps/bader/workflows/__init__.py
simmate/apps/bader/workflows/badelf.py
simmate/apps/bader/workflows/bader.py
simmate/apps/bader/workflows/bader_dev.py
simmate/apps/bader/workflows/combine_chgcars.py
simmate/apps/bcpc/__init__.py
simmate/apps/bcpc/migrations/0001_setup.py
simmate/apps/bcpc/migrations/0002_initial.py
simmate/apps/bcpc/migrations/__init__.py
simmate/apps/bcpc/models/__init__.py
simmate/apps/bcpc/models/iso_pesticides.py
simmate-0.18.0.dist-info/licenses/LICENSE
simmate-0.18.0.dist-info/METADATA
simmate-0.18.0.dist-info/WHEEL
simmate-0.18.0.dist-info/entry_points.txt
simmate-0.18.0.dist-info/top_level.txt
simmate-0.18.0.dist-info/RECORD
